{"assets":[{"id":"1cQeGCHnzN_vrrBmPHODg","layers":[{"ddd":0,"ind":4,"ty":4,"ln":"layer_4","sr":1,"ks":{"a":{"a":0,"k":[6,7.875]},"o":{"a":0,"k":100},"p":{"a":1,"k":[{"t":0,"s":[849,846.5],"i":{"x":0,"y":0},"o":{"x":1,"y":1}},{"t":77,"s":[849,846.5],"i":{"x":0,"y":0},"o":{"x":1,"y":1}},{"t":78,"s":[849.08,846.54],"i":{"x":0,"y":0},"o":{"x":1,"y":1}},{"t":79,"s":[849.19,846.6],"i":{"x":0,"y":0},"o":{"x":1,"y":1}},{"t":80,"s":[849.34,846.67],"i":{"x":0,"y":0},"o":{"x":1,"y":1}},{"t":81,"s":[849.52,846.76],"i":{"x":0,"y":0},"o":{"x":1,"y":1}},{"t":82,"s":[849.74,846.87],"i":{"x":0,"y":0},"o":{"x":1,"y":1}},{"t":83,"s":[849.99,847],"i":{"x":0,"y":0},"o":{"x":1,"y":1}},{"t":84,"s":[850.28,847.14],"i":{"x":0,"y":0},"o":{"x":1,"y":1}},{"t":85,"s":[850.6,847.3],"i":{"x":0,"y":0},"o":{"x":1,"y":1}},{"t":86,"s":[850.94,847.47],"i":{"x":0,"y":0},"o":{"x":1,"y":1}},{"t":87,"s":[851.29,847.64],"i":{"x":0,"y":0},"o":{"x":1,"y":1}},{"t":88,"s":[851.64,847.82],"i":{"x":0,"y":0},"o":{"x":1,"y":1}},{"t":89,"s":[852,848],"i":{"x":0,"y":0},"o":{"x":1,"y":1}},{"t":90,"s":[852.35,848.17],"i":{"x":0,"y":0},"o":{"x":1,"y":1}},{"t":91,"s":[852.68,848.34],"i":{"x":0,"y":0},"o":{"x":1,"y":1}},{"t":92,"s":[853,848.5],"i":{"x":0,"y":0},"o":{"x":1,"y":1}},{"t":93,"s":[853.31,848.65],"i":{"x":0,"y":0},"o":{"x":1,"y":1}},{"t":94,"s":[853.59,848.8],"i":{"x":0,"y":0},"o":{"x":1,"y":1}},{"t":95,"s":[853.86,848.93],"i":{"x":0,"y":0},"o":{"x":1,"y":1}},{"t":96,"s":[854.12,849.06],"i":{"x":0,"y":0},"o":{"x":1,"y":1}},{"t":97,"s":[854.35,849.18],"i":{"x":0,"y":0},"o":{"x":1,"y":1}},{"t":98,"s":[854.58,849.29],"i":{"x":0,"y":0},"o":{"x":1,"y":1}},{"t":99,"s":[854.78,849.39],"i":{"x":0,"y":0},"o":{"x":1,"y":1}},{"t":100,"s":[854.98,849.49],"i":{"x":0,"y":0},"o":{"x":1,"y":1}},{"t":101,"s":[855.16,849.58],"i":{"x":0,"y":0},"o":{"x":1,"y":1}},{"t":102,"s":[855.32,849.66],"i":{"x":0,"y":0},"o":{"x":1,"y":1}},{"t":103,"s":[855.48,849.74],"i":{"x":0,"y":0},"o":{"x":1,"y":1}},{"t":104,"s":[855.62,849.81],"i":{"x":0,"y":0},"o":{"x":1,"y":1}},{"t":105,"s":[855.76,849.88],"i":{"x":0,"y":0},"o":{"x":1,"y":1}},{"t":106,"s":[855.89,849.94],"i":{"x":0,"y":0},"o":{"x":1,"y":1}},{"t":107,"s":[856,850],"i":{"x":0,"y":0},"o":{"x":1,"y":1}},{"t":108,"s":[856.11,850.05],"i":{"x":0,"y":0},"o":{"x":1,"y":1}},{"t":109,"s":[856.21,850.1],"i":{"x":0,"y":0},"o":{"x":1,"y":1}},{"t":110,"s":[856.3,850.15],"i":{"x":0,"y":0},"o":{"x":1,"y":1}},{"t":111,"s":[856.39,850.19],"i":{"x":0,"y":0},"o":{"x":1,"y":1}},{"t":112,"s":[856.46,850.23],"i":{"x":0,"y":0},"o":{"x":1,"y":1}},{"t":113,"s":[856.54,850.27],"i":{"x":0,"y":0},"o":{"x":1,"y":1}},{"t":114,"s":[856.6,850.3],"i":{"x":0,"y":0},"o":{"x":1,"y":1}},{"t":115,"s":[856.66,850.33],"i":{"x":0,"y":0},"o":{"x":1,"y":1}},{"t":116,"s":[856.71,850.36],"i":{"x":0,"y":0},"o":{"x":1,"y":1}},{"t":117,"s":[856.76,850.38],"i":{"x":0,"y":0},"o":{"x":1,"y":1}},{"t":118,"s":[856.81,850.4],"i":{"x":0,"y":0},"o":{"x":1,"y":1}},{"t":119,"s":[856.84,850.42],"i":{"x":0,"y":0},"o":{"x":1,"y":1}},{"t":120,"s":[856.88,850.44],"i":{"x":0,"y":0},"o":{"x":1,"y":1}},{"t":121,"s":[856.91,850.45],"i":{"x":0,"y":0},"o":{"x":1,"y":1}},{"t":122,"s":[856.93,850.47],"i":{"x":0,"y":0},"o":{"x":1,"y":1}},{"t":123,"s":[856.95,850.48],"i":{"x":0,"y":0},"o":{"x":1,"y":1}},{"t":124,"s":[856.97,850.48],"i":{"x":0,"y":0},"o":{"x":1,"y":1}},{"t":125,"s":[856.98,850.49],"i":{"x":0,"y":0},"o":{"x":1,"y":1}},{"t":126,"s":[856.99,850.5],"i":{"x":0,"y":0},"o":{"x":1,"y":1}},{"t":127,"s":[857,850.5],"i":{"x":0,"y":0},"o":{"x":1,"y":1}},{"t":128,"s":[857,850.5],"i":{"x":0,"y":0},"o":{"x":1,"y":1}},{"t":129,"s":[856.95,850.47],"i":{"x":0,"y":0},"o":{"x":1,"y":1}},{"t":130,"s":[856.85,850.42],"i":{"x":0,"y":0},"o":{"x":1,"y":1}},{"t":131,"s":[856.71,850.36],"i":{"x":0,"y":0},"o":{"x":1,"y":1}},{"t":132,"s":[856.54,850.27],"i":{"x":0,"y":0},"o":{"x":1,"y":1}},{"t":133,"s":[856.33,850.17],"i":{"x":0,"y":0},"o":{"x":1,"y":1}},{"t":134,"s":[856.09,850.04],"i":{"x":0,"y":0},"o":{"x":1,"y":1}},{"t":135,"s":[855.81,849.91],"i":{"x":0,"y":0},"o":{"x":1,"y":1}},{"t":136,"s":[855.5,849.75],"i":{"x":0,"y":0},"o":{"x":1,"y":1}},{"t":137,"s":[855.17,849.59],"i":{"x":0,"y":0},"o":{"x":1,"y":1}},{"t":138,"s":[854.82,849.41],"i":{"x":0,"y":0},"o":{"x":1,"y":1}},{"t":139,"s":[854.47,849.23],"i":{"x":0,"y":0},"o":{"x":1,"y":1}},{"t":140,"s":[854.11,849.06],"i":{"x":0,"y":0},"o":{"x":1,"y":1}},{"t":141,"s":[853.76,848.88],"i":{"x":0,"y":0},"o":{"x":1,"y":1}},{"t":142,"s":[853.42,848.71],"i":{"x":0,"y":0},"o":{"x":1,"y":1}},{"t":143,"s":[853.1,848.55],"i":{"x":0,"y":0},"o":{"x":1,"y":1}},{"t":144,"s":[852.79,848.39],"i":{"x":0,"y":0},"o":{"x":1,"y":1}},{"t":145,"s":[852.5,848.25],"i":{"x":0,"y":0},"o":{"x":1,"y":1}},{"t":146,"s":[852.22,848.11],"i":{"x":0,"y":0},"o":{"x":1,"y":1}},{"t":147,"s":[851.96,847.98],"i":{"x":0,"y":0},"o":{"x":1,"y":1}},{"t":148,"s":[851.72,847.86],"i":{"x":0,"y":0},"o":{"x":1,"y":1}},{"t":149,"s":[851.49,847.75],"i":{"x":0,"y":0},"o":{"x":1,"y":1}},{"t":150,"s":[851.28,847.64],"i":{"x":0,"y":0},"o":{"x":1,"y":1}},{"t":151,"s":[851.08,847.54],"i":{"x":0,"y":0},"o":{"x":1,"y":1}},{"t":152,"s":[850.9,847.45],"i":{"x":0,"y":0},"o":{"x":1,"y":1}},{"t":153,"s":[850.73,847.36],"i":{"x":0,"y":0},"o":{"x":1,"y":1}},{"t":154,"s":[850.57,847.28],"i":{"x":0,"y":0},"o":{"x":1,"y":1}},{"t":155,"s":[850.42,847.21],"i":{"x":0,"y":0},"o":{"x":1,"y":1}},{"t":156,"s":[850.28,847.14],"i":{"x":0,"y":0},"o":{"x":1,"y":1}},{"t":157,"s":[850.15,847.08],"i":{"x":0,"y":0},"o":{"x":1,"y":1}},{"t":158,"s":[850.03,847.02],"i":{"x":0,"y":0},"o":{"x":1,"y":1}},{"t":159,"s":[849.92,846.96],"i":{"x":0,"y":0},"o":{"x":1,"y":1}},{"t":160,"s":[849.82,846.91],"i":{"x":0,"y":0},"o":{"x":1,"y":1}},{"t":161,"s":[849.73,846.86],"i":{"x":0,"y":0},"o":{"x":1,"y":1}},{"t":162,"s":[849.64,846.82],"i":{"x":0,"y":0},"o":{"x":1,"y":1}},{"t":163,"s":[849.56,846.78],"i":{"x":0,"y":0},"o":{"x":1,"y":1}},{"t":164,"s":[849.49,846.74],"i":{"x":0,"y":0},"o":{"x":1,"y":1}},{"t":165,"s":[849.42,846.71],"i":{"x":0,"y":0},"o":{"x":1,"y":1}},{"t":166,"s":[849.36,846.68],"i":{"x":0,"y":0},"o":{"x":1,"y":1}},{"t":167,"s":[849.3,846.65],"i":{"x":0,"y":0},"o":{"x":1,"y":1}},{"t":168,"s":[849.25,846.63],"i":{"x":0,"y":0},"o":{"x":1,"y":1}},{"t":169,"s":[849.21,846.6],"i":{"x":0,"y":0},"o":{"x":1,"y":1}},{"t":170,"s":[849.17,846.58],"i":{"x":0,"y":0},"o":{"x":1,"y":1}},{"t":171,"s":[849.13,846.57],"i":{"x":0,"y":0},"o":{"x":1,"y":1}},{"t":172,"s":[849.1,846.55],"i":{"x":0,"y":0},"o":{"x":1,"y":1}},{"t":173,"s":[849.08,846.54],"i":{"x":0,"y":0},"o":{"x":1,"y":1}},{"t":174,"s":[849.05,846.53],"i":{"x":0,"y":0},"o":{"x":1,"y":1}},{"t":175,"s":[849.04,846.52],"i":{"x":0,"y":0},"o":{"x":1,"y":1}},{"t":176,"s":[849.02,846.51],"i":{"x":0,"y":0},"o":{"x":1,"y":1}},{"t":177,"s":[849.01,846.51],"i":{"x":0,"y":0},"o":{"x":1,"y":1}},{"t":178,"s":[849,846.5],"i":{"x":0,"y":0},"o":{"x":1,"y":1}}]},"r":{"a":0,"k":0},"s":{"a":0,"k":[133.33,133.33]},"sk":{"a":0,"k":0},"sa":{"a":0,"k":0}},"ao":0,"ip":0,"op":180,"st":0,"bm":0,"shapes":[{"ty":"gr","nm":"surface1","it":[{"ty":"gr","it":[{"ty":"sh","d":1,"ks":{"a":0,"k":{"c":true,"i":[[0,0],[0,0],[1.07,-0.54],[0,0],[0.27,0],[0.3,0.19],[0,0.63],[0,0],[-1.07,0.54],[0,0],[0,0],[-0.54,-0.34],[0,-0.62]],"o":[[0,0],[0,1.19],[0,0],[-0.25,0.13],[-0.32,0],[-0.53,-0.33],[0,0],[0,-1.2],[0,0],[0,0],[0.56,-0.29],[0.52,0.32],[0,0]],"v":[[11.79,1.94],[11.79,8.85],[10.05,11.65],[2.74,15.31],[1.94,15.5],[0.99,15.23],[0.14,13.7],[0.14,6.8],[1.88,3.99],[4.56,2.65],[9.19,0.34],[10.94,0.41],[11.79,1.94]]}}},{"ty":"fl","c":{"a":0,"k":[1,1,1,1]},"r":1,"o":{"a":0,"k":100}},{"ty":"tr","nm":"Transform","a":{"a":0,"k":[0,0]},"o":{"a":0,"k":100},"p":{"a":0,"k":[0,0]},"r":{"a":0,"k":0},"s":{"a":0,"k":[100,100]},"sk":{"a":0,"k":0},"sa":{"a":0,"k":0}}]},{"ty":"tr","nm":"Transform","a":{"a":0,"k":[0,0]},"o":{"a":0,"k":100},"p":{"a":0,"k":[0,0]},"r":{"a":0,"k":0},"s":{"a":0,"k":[100,100]},"sk":{"a":0,"k":0},"sa":{"a":0,"k":0}}]}]},{"ddd":0,"ind":5,"ty":4,"ln":"layer_5","sr":1,"ks":{"a":{"a":0,"k":[6,7.875]},"o":{"a":0,"k":100},"p":{"a":1,"k":[{"t":0,"s":[831,846.5],"i":{"x":0,"y":0},"o":{"x":1,"y":1}},{"t":77,"s":[831,846.5],"i":{"x":0,"y":0},"o":{"x":1,"y":1}},{"t":78,"s":[830.92,846.54],"i":{"x":0,"y":0},"o":{"x":1,"y":1}},{"t":79,"s":[830.81,846.6],"i":{"x":0,"y":0},"o":{"x":1,"y":1}},{"t":80,"s":[830.66,846.67],"i":{"x":0,"y":0},"o":{"x":1,"y":1}},{"t":81,"s":[830.48,846.76],"i":{"x":0,"y":0},"o":{"x":1,"y":1}},{"t":82,"s":[830.26,846.87],"i":{"x":0,"y":0},"o":{"x":1,"y":1}},{"t":83,"s":[830.01,847],"i":{"x":0,"y":0},"o":{"x":1,"y":1}},{"t":84,"s":[829.72,847.14],"i":{"x":0,"y":0},"o":{"x":1,"y":1}},{"t":85,"s":[829.4,847.3],"i":{"x":0,"y":0},"o":{"x":1,"y":1}},{"t":86,"s":[829.06,847.47],"i":{"x":0,"y":0},"o":{"x":1,"y":1}},{"t":87,"s":[828.71,847.64],"i":{"x":0,"y":0},"o":{"x":1,"y":1}},{"t":88,"s":[828.36,847.82],"i":{"x":0,"y":0},"o":{"x":1,"y":1}},{"t":89,"s":[828,848],"i":{"x":0,"y":0},"o":{"x":1,"y":1}},{"t":90,"s":[827.65,848.17],"i":{"x":0,"y":0},"o":{"x":1,"y":1}},{"t":91,"s":[827.32,848.34],"i":{"x":0,"y":0},"o":{"x":1,"y":1}},{"t":92,"s":[827,848.5],"i":{"x":0,"y":0},"o":{"x":1,"y":1}},{"t":93,"s":[826.69,848.65],"i":{"x":0,"y":0},"o":{"x":1,"y":1}},{"t":94,"s":[826.41,848.8],"i":{"x":0,"y":0},"o":{"x":1,"y":1}},{"t":95,"s":[826.14,848.93],"i":{"x":0,"y":0},"o":{"x":1,"y":1}},{"t":96,"s":[825.88,849.06],"i":{"x":0,"y":0},"o":{"x":1,"y":1}},{"t":97,"s":[825.65,849.18],"i":{"x":0,"y":0},"o":{"x":1,"y":1}},{"t":98,"s":[825.42,849.29],"i":{"x":0,"y":0},"o":{"x":1,"y":1}},{"t":99,"s":[825.22,849.39],"i":{"x":0,"y":0},"o":{"x":1,"y":1}},{"t":100,"s":[825.02,849.49],"i":{"x":0,"y":0},"o":{"x":1,"y":1}},{"t":101,"s":[824.84,849.58],"i":{"x":0,"y":0},"o":{"x":1,"y":1}},{"t":102,"s":[824.68,849.66],"i":{"x":0,"y":0},"o":{"x":1,"y":1}},{"t":103,"s":[824.52,849.74],"i":{"x":0,"y":0},"o":{"x":1,"y":1}},{"t":104,"s":[824.38,849.81],"i":{"x":0,"y":0},"o":{"x":1,"y":1}},{"t":105,"s":[824.24,849.88],"i":{"x":0,"y":0},"o":{"x":1,"y":1}},{"t":106,"s":[824.11,849.94],"i":{"x":0,"y":0},"o":{"x":1,"y":1}},{"t":107,"s":[824,850],"i":{"x":0,"y":0},"o":{"x":1,"y":1}},{"t":108,"s":[823.89,850.05],"i":{"x":0,"y":0},"o":{"x":1,"y":1}},{"t":109,"s":[823.79,850.1],"i":{"x":0,"y":0},"o":{"x":1,"y":1}},{"t":110,"s":[823.7,850.15],"i":{"x":0,"y":0},"o":{"x":1,"y":1}},{"t":111,"s":[823.61,850.19],"i":{"x":0,"y":0},"o":{"x":1,"y":1}},{"t":112,"s":[823.54,850.23],"i":{"x":0,"y":0},"o":{"x":1,"y":1}},{"t":113,"s":[823.46,850.27],"i":{"x":0,"y":0},"o":{"x":1,"y":1}},{"t":114,"s":[823.4,850.3],"i":{"x":0,"y":0},"o":{"x":1,"y":1}},{"t":115,"s":[823.34,850.33],"i":{"x":0,"y":0},"o":{"x":1,"y":1}},{"t":116,"s":[823.29,850.36],"i":{"x":0,"y":0},"o":{"x":1,"y":1}},{"t":117,"s":[823.24,850.38],"i":{"x":0,"y":0},"o":{"x":1,"y":1}},{"t":118,"s":[823.19,850.4],"i":{"x":0,"y":0},"o":{"x":1,"y":1}},{"t":119,"s":[823.16,850.42],"i":{"x":0,"y":0},"o":{"x":1,"y":1}},{"t":120,"s":[823.12,850.44],"i":{"x":0,"y":0},"o":{"x":1,"y":1}},{"t":121,"s":[823.09,850.45],"i":{"x":0,"y":0},"o":{"x":1,"y":1}},{"t":122,"s":[823.07,850.47],"i":{"x":0,"y":0},"o":{"x":1,"y":1}},{"t":123,"s":[823.05,850.48],"i":{"x":0,"y":0},"o":{"x":1,"y":1}},{"t":124,"s":[823.03,850.48],"i":{"x":0,"y":0},"o":{"x":1,"y":1}},{"t":125,"s":[823.02,850.49],"i":{"x":0,"y":0},"o":{"x":1,"y":1}},{"t":126,"s":[823.01,850.5],"i":{"x":0,"y":0},"o":{"x":1,"y":1}},{"t":127,"s":[823,850.5],"i":{"x":0,"y":0},"o":{"x":1,"y":1}},{"t":128,"s":[823,850.5],"i":{"x":0,"y":0},"o":{"x":1,"y":1}},{"t":129,"s":[823.05,850.47],"i":{"x":0,"y":0},"o":{"x":1,"y":1}},{"t":130,"s":[823.15,850.42],"i":{"x":0,"y":0},"o":{"x":1,"y":1}},{"t":131,"s":[823.29,850.36],"i":{"x":0,"y":0},"o":{"x":1,"y":1}},{"t":132,"s":[823.46,850.27],"i":{"x":0,"y":0},"o":{"x":1,"y":1}},{"t":133,"s":[823.67,850.17],"i":{"x":0,"y":0},"o":{"x":1,"y":1}},{"t":134,"s":[823.91,850.04],"i":{"x":0,"y":0},"o":{"x":1,"y":1}},{"t":135,"s":[824.19,849.91],"i":{"x":0,"y":0},"o":{"x":1,"y":1}},{"t":136,"s":[824.5,849.75],"i":{"x":0,"y":0},"o":{"x":1,"y":1}},{"t":137,"s":[824.83,849.59],"i":{"x":0,"y":0},"o":{"x":1,"y":1}},{"t":138,"s":[825.18,849.41],"i":{"x":0,"y":0},"o":{"x":1,"y":1}},{"t":139,"s":[825.53,849.23],"i":{"x":0,"y":0},"o":{"x":1,"y":1}},{"t":140,"s":[825.89,849.06],"i":{"x":0,"y":0},"o":{"x":1,"y":1}},{"t":141,"s":[826.24,848.88],"i":{"x":0,"y":0},"o":{"x":1,"y":1}},{"t":142,"s":[826.58,848.71],"i":{"x":0,"y":0},"o":{"x":1,"y":1}},{"t":143,"s":[826.9,848.55],"i":{"x":0,"y":0},"o":{"x":1,"y":1}},{"t":144,"s":[827.21,848.39],"i":{"x":0,"y":0},"o":{"x":1,"y":1}},{"t":145,"s":[827.5,848.25],"i":{"x":0,"y":0},"o":{"x":1,"y":1}},{"t":146,"s":[827.78,848.11],"i":{"x":0,"y":0},"o":{"x":1,"y":1}},{"t":147,"s":[828.04,847.98],"i":{"x":0,"y":0},"o":{"x":1,"y":1}},{"t":148,"s":[828.28,847.86],"i":{"x":0,"y":0},"o":{"x":1,"y":1}},{"t":149,"s":[828.51,847.75],"i":{"x":0,"y":0},"o":{"x":1,"y":1}},{"t":150,"s":[828.72,847.64],"i":{"x":0,"y":0},"o":{"x":1,"y":1}},{"t":151,"s":[828.92,847.54],"i":{"x":0,"y":0},"o":{"x":1,"y":1}},{"t":152,"s":[829.1,847.45],"i":{"x":0,"y":0},"o":{"x":1,"y":1}},{"t":153,"s":[829.27,847.36],"i":{"x":0,"y":0},"o":{"x":1,"y":1}},{"t":154,"s":[829.43,847.28],"i":{"x":0,"y":0},"o":{"x":1,"y":1}},{"t":155,"s":[829.58,847.21],"i":{"x":0,"y":0},"o":{"x":1,"y":1}},{"t":156,"s":[829.72,847.14],"i":{"x":0,"y":0},"o":{"x":1,"y":1}},{"t":157,"s":[829.85,847.08],"i":{"x":0,"y":0},"o":{"x":1,"y":1}},{"t":158,"s":[829.97,847.02],"i":{"x":0,"y":0},"o":{"x":1,"y":1}},{"t":159,"s":[830.08,846.96],"i":{"x":0,"y":0},"o":{"x":1,"y":1}},{"t":160,"s":[830.18,846.91],"i":{"x":0,"y":0},"o":{"x":1,"y":1}},{"t":161,"s":[830.27,846.86],"i":{"x":0,"y":0},"o":{"x":1,"y":1}},{"t":162,"s":[830.36,846.82],"i":{"x":0,"y":0},"o":{"x":1,"y":1}},{"t":163,"s":[830.44,846.78],"i":{"x":0,"y":0},"o":{"x":1,"y":1}},{"t":164,"s":[830.51,846.74],"i":{"x":0,"y":0},"o":{"x":1,"y":1}},{"t":165,"s":[830.58,846.71],"i":{"x":0,"y":0},"o":{"x":1,"y":1}},{"t":166,"s":[830.64,846.68],"i":{"x":0,"y":0},"o":{"x":1,"y":1}},{"t":167,"s":[830.7,846.65],"i":{"x":0,"y":0},"o":{"x":1,"y":1}},{"t":168,"s":[830.75,846.63],"i":{"x":0,"y":0},"o":{"x":1,"y":1}},{"t":169,"s":[830.79,846.6],"i":{"x":0,"y":0},"o":{"x":1,"y":1}},{"t":170,"s":[830.83,846.58],"i":{"x":0,"y":0},"o":{"x":1,"y":1}},{"t":171,"s":[830.87,846.57],"i":{"x":0,"y":0},"o":{"x":1,"y":1}},{"t":172,"s":[830.9,846.55],"i":{"x":0,"y":0},"o":{"x":1,"y":1}},{"t":173,"s":[830.92,846.54],"i":{"x":0,"y":0},"o":{"x":1,"y":1}},{"t":174,"s":[830.95,846.53],"i":{"x":0,"y":0},"o":{"x":1,"y":1}},{"t":175,"s":[830.96,846.52],"i":{"x":0,"y":0},"o":{"x":1,"y":1}},{"t":176,"s":[830.98,846.51],"i":{"x":0,"y":0},"o":{"x":1,"y":1}},{"t":177,"s":[830.99,846.51],"i":{"x":0,"y":0},"o":{"x":1,"y":1}},{"t":178,"s":[831,846.5],"i":{"x":0,"y":0},"o":{"x":1,"y":1}}]},"r":{"a":0,"k":0},"s":{"a":0,"k":[133.33,133.33]},"sk":{"a":0,"k":0},"sa":{"a":0,"k":0}},"ao":0,"ip":0,"op":180,"st":0,"bm":0,"shapes":[{"ty":"gr","nm":"surface6","it":[{"ty":"gr","it":[{"ty":"sh","d":1,"ks":{"a":0,"k":{"c":true,"i":[[0,0],[0,0],[0.54,-0.33],[0,-0.62],[0,0],[-1.07,-0.54],[0,0],[-0.27,0],[-0.29,0.19],[0,0.63],[0,0],[1.07,0.54]],"o":[[0,0],[-0.56,-0.29],[-0.54,0.32],[0,0],[0,1.2],[0,0],[0.25,0.13],[0.32,0],[0.54,-0.33],[0,0],[0.01,-1.19],[0,0]],"v":[[10.13,3.99],[2.81,0.34],[1.06,0.41],[0.21,1.94],[0.21,8.85],[1.95,11.66],[9.26,15.31],[10.06,15.5],[11,15.23],[11.85,13.7],[11.85,6.79],[10.13,3.99]]}}},{"ty":"fl","c":{"a":0,"k":[1,1,1,1]},"r":1,"o":{"a":0,"k":100}},{"ty":"tr","nm":"Transform","a":{"a":0,"k":[0,0]},"o":{"a":0,"k":100},"p":{"a":0,"k":[0,0]},"r":{"a":0,"k":0},"s":{"a":0,"k":[100,100]},"sk":{"a":0,"k":0},"sa":{"a":0,"k":0}}]},{"ty":"tr","nm":"Transform","a":{"a":0,"k":[0,0]},"o":{"a":0,"k":100},"p":{"a":0,"k":[0,0]},"r":{"a":0,"k":0},"s":{"a":0,"k":[100,100]},"sk":{"a":0,"k":0},"sa":{"a":0,"k":0}}]}]},{"ddd":0,"ind":6,"ty":4,"ln":"layer_6","sr":1,"ks":{"a":{"a":0,"k":[10.5,6.375]},"o":{"a":0,"k":100},"p":{"a":1,"k":[{"t":0,"s":[840,831.5],"i":{"x":0,"y":0},"o":{"x":1,"y":1}},{"t":77,"s":[840,831.5],"i":{"x":0,"y":0},"o":{"x":1,"y":1}},{"t":78,"s":[840,831.43],"i":{"x":0,"y":0},"o":{"x":1,"y":1}},{"t":79,"s":[840,831.33],"i":{"x":0,"y":0},"o":{"x":1,"y":1}},{"t":80,"s":[840,831.2],"i":{"x":0,"y":0},"o":{"x":1,"y":1}},{"t":81,"s":[840,831.04],"i":{"x":0,"y":0},"o":{"x":1,"y":1}},{"t":82,"s":[840,830.85],"i":{"x":0,"y":0},"o":{"x":1,"y":1}},{"t":83,"s":[840,830.63],"i":{"x":0,"y":0},"o":{"x":1,"y":1}},{"t":84,"s":[840,830.38],"i":{"x":0,"y":0},"o":{"x":1,"y":1}},{"t":85,"s":[840,830.1],"i":{"x":0,"y":0},"o":{"x":1,"y":1}},{"t":86,"s":[840,829.81],"i":{"x":0,"y":0},"o":{"x":1,"y":1}},{"t":87,"s":[840,829.5],"i":{"x":0,"y":0},"o":{"x":1,"y":1}},{"t":88,"s":[840,829.19],"i":{"x":0,"y":0},"o":{"x":1,"y":1}},{"t":89,"s":[840,828.88],"i":{"x":0,"y":0},"o":{"x":1,"y":1}},{"t":90,"s":[840,828.57],"i":{"x":0,"y":0},"o":{"x":1,"y":1}},{"t":91,"s":[840,828.28],"i":{"x":0,"y":0},"o":{"x":1,"y":1}},{"t":92,"s":[840,828],"i":{"x":0,"y":0},"o":{"x":1,"y":1}},{"t":93,"s":[840,827.73],"i":{"x":0,"y":0},"o":{"x":1,"y":1}},{"t":94,"s":[840,827.48],"i":{"x":0,"y":0},"o":{"x":1,"y":1}},{"t":95,"s":[840,827.25],"i":{"x":0,"y":0},"o":{"x":1,"y":1}},{"t":96,"s":[840,827.02],"i":{"x":0,"y":0},"o":{"x":1,"y":1}},{"t":97,"s":[840,826.82],"i":{"x":0,"y":0},"o":{"x":1,"y":1}},{"t":98,"s":[840,826.62],"i":{"x":0,"y":0},"o":{"x":1,"y":1}},{"t":99,"s":[840,826.44],"i":{"x":0,"y":0},"o":{"x":1,"y":1}},{"t":100,"s":[840,826.27],"i":{"x":0,"y":0},"o":{"x":1,"y":1}},{"t":101,"s":[840,826.11],"i":{"x":0,"y":0},"o":{"x":1,"y":1}},{"t":102,"s":[840,825.97],"i":{"x":0,"y":0},"o":{"x":1,"y":1}},{"t":103,"s":[840,825.83],"i":{"x":0,"y":0},"o":{"x":1,"y":1}},{"t":104,"s":[840,825.7],"i":{"x":0,"y":0},"o":{"x":1,"y":1}},{"t":105,"s":[840,825.59],"i":{"x":0,"y":0},"o":{"x":1,"y":1}},{"t":106,"s":[840,825.48],"i":{"x":0,"y":0},"o":{"x":1,"y":1}},{"t":107,"s":[840,825.37],"i":{"x":0,"y":0},"o":{"x":1,"y":1}},{"t":108,"s":[840,825.28],"i":{"x":0,"y":0},"o":{"x":1,"y":1}},{"t":109,"s":[840,825.19],"i":{"x":0,"y":0},"o":{"x":1,"y":1}},{"t":110,"s":[840,825.11],"i":{"x":0,"y":0},"o":{"x":1,"y":1}},{"t":111,"s":[840,825.04],"i":{"x":0,"y":0},"o":{"x":1,"y":1}},{"t":112,"s":[840,824.97],"i":{"x":0,"y":0},"o":{"x":1,"y":1}},{"t":113,"s":[840,824.91],"i":{"x":0,"y":0},"o":{"x":1,"y":1}},{"t":114,"s":[840,824.85],"i":{"x":0,"y":0},"o":{"x":1,"y":1}},{"t":115,"s":[840,824.8],"i":{"x":0,"y":0},"o":{"x":1,"y":1}},{"t":116,"s":[840,824.75],"i":{"x":0,"y":0},"o":{"x":1,"y":1}},{"t":117,"s":[840,824.71],"i":{"x":0,"y":0},"o":{"x":1,"y":1}},{"t":118,"s":[840,824.67],"i":{"x":0,"y":0},"o":{"x":1,"y":1}},{"t":119,"s":[840,824.64],"i":{"x":0,"y":0},"o":{"x":1,"y":1}},{"t":120,"s":[840,824.61],"i":{"x":0,"y":0},"o":{"x":1,"y":1}},{"t":121,"s":[840,824.58],"i":{"x":0,"y":0},"o":{"x":1,"y":1}},{"t":122,"s":[840,824.56],"i":{"x":0,"y":0},"o":{"x":1,"y":1}},{"t":123,"s":[840,824.54],"i":{"x":0,"y":0},"o":{"x":1,"y":1}},{"t":124,"s":[840,824.53],"i":{"x":0,"y":0},"o":{"x":1,"y":1}},{"t":125,"s":[840,824.52],"i":{"x":0,"y":0},"o":{"x":1,"y":1}},{"t":126,"s":[840,824.51],"i":{"x":0,"y":0},"o":{"x":1,"y":1}},{"t":127,"s":[840,824.5],"i":{"x":0,"y":0},"o":{"x":1,"y":1}},{"t":128,"s":[840,824.5],"i":{"x":0,"y":0},"o":{"x":1,"y":1}},{"t":129,"s":[840,824.55],"i":{"x":0,"y":0},"o":{"x":1,"y":1}},{"t":130,"s":[840,824.64],"i":{"x":0,"y":0},"o":{"x":1,"y":1}},{"t":131,"s":[840,824.75],"i":{"x":0,"y":0},"o":{"x":1,"y":1}},{"t":132,"s":[840,824.9],"i":{"x":0,"y":0},"o":{"x":1,"y":1}},{"t":133,"s":[840,825.08],"i":{"x":0,"y":0},"o":{"x":1,"y":1}},{"t":134,"s":[840,825.3],"i":{"x":0,"y":0},"o":{"x":1,"y":1}},{"t":135,"s":[840,825.54],"i":{"x":0,"y":0},"o":{"x":1,"y":1}},{"t":136,"s":[840,825.81],"i":{"x":0,"y":0},"o":{"x":1,"y":1}},{"t":137,"s":[840,826.1],"i":{"x":0,"y":0},"o":{"x":1,"y":1}},{"t":138,"s":[840,826.4],"i":{"x":0,"y":0},"o":{"x":1,"y":1}},{"t":139,"s":[840,826.71],"i":{"x":0,"y":0},"o":{"x":1,"y":1}},{"t":140,"s":[840,827.03],"i":{"x":0,"y":0},"o":{"x":1,"y":1}},{"t":141,"s":[840,827.33],"i":{"x":0,"y":0},"o":{"x":1,"y":1}},{"t":142,"s":[840,827.63],"i":{"x":0,"y":0},"o":{"x":1,"y":1}},{"t":143,"s":[840,827.91],"i":{"x":0,"y":0},"o":{"x":1,"y":1}},{"t":144,"s":[840,828.18],"i":{"x":0,"y":0},"o":{"x":1,"y":1}},{"t":145,"s":[840,828.44],"i":{"x":0,"y":0},"o":{"x":1,"y":1}},{"t":146,"s":[840,828.68],"i":{"x":0,"y":0},"o":{"x":1,"y":1}},{"t":147,"s":[840,828.91],"i":{"x":0,"y":0},"o":{"x":1,"y":1}},{"t":148,"s":[840,829.12],"i":{"x":0,"y":0},"o":{"x":1,"y":1}},{"t":149,"s":[840,829.32],"i":{"x":0,"y":0},"o":{"x":1,"y":1}},{"t":150,"s":[840,829.5],"i":{"x":0,"y":0},"o":{"x":1,"y":1}},{"t":151,"s":[840,829.68],"i":{"x":0,"y":0},"o":{"x":1,"y":1}},{"t":152,"s":[840,829.84],"i":{"x":0,"y":0},"o":{"x":1,"y":1}},{"t":153,"s":[840,829.99],"i":{"x":0,"y":0},"o":{"x":1,"y":1}},{"t":154,"s":[840,830.13],"i":{"x":0,"y":0},"o":{"x":1,"y":1}},{"t":155,"s":[840,830.26],"i":{"x":0,"y":0},"o":{"x":1,"y":1}},{"t":156,"s":[840,830.38],"i":{"x":0,"y":0},"o":{"x":1,"y":1}},{"t":157,"s":[840,830.49],"i":{"x":0,"y":0},"o":{"x":1,"y":1}},{"t":158,"s":[840,830.59],"i":{"x":0,"y":0},"o":{"x":1,"y":1}},{"t":159,"s":[840,830.69],"i":{"x":0,"y":0},"o":{"x":1,"y":1}},{"t":160,"s":[840,830.78],"i":{"x":0,"y":0},"o":{"x":1,"y":1}},{"t":161,"s":[840,830.86],"i":{"x":0,"y":0},"o":{"x":1,"y":1}},{"t":162,"s":[840,830.94],"i":{"x":0,"y":0},"o":{"x":1,"y":1}},{"t":163,"s":[840,831.01],"i":{"x":0,"y":0},"o":{"x":1,"y":1}},{"t":164,"s":[840,831.07],"i":{"x":0,"y":0},"o":{"x":1,"y":1}},{"t":165,"s":[840,831.13],"i":{"x":0,"y":0},"o":{"x":1,"y":1}},{"t":166,"s":[840,831.19],"i":{"x":0,"y":0},"o":{"x":1,"y":1}},{"t":167,"s":[840,831.23],"i":{"x":0,"y":0},"o":{"x":1,"y":1}},{"t":168,"s":[840,831.28],"i":{"x":0,"y":0},"o":{"x":1,"y":1}},{"t":169,"s":[840,831.32],"i":{"x":0,"y":0},"o":{"x":1,"y":1}},{"t":170,"s":[840,831.35],"i":{"x":0,"y":0},"o":{"x":1,"y":1}},{"t":171,"s":[840,831.38],"i":{"x":0,"y":0},"o":{"x":1,"y":1}},{"t":172,"s":[840,831.41],"i":{"x":0,"y":0},"o":{"x":1,"y":1}},{"t":173,"s":[840,831.43],"i":{"x":0,"y":0},"o":{"x":1,"y":1}},{"t":174,"s":[840,831.45],"i":{"x":0,"y":0},"o":{"x":1,"y":1}},{"t":175,"s":[840,831.47],"i":{"x":0,"y":0},"o":{"x":1,"y":1}},{"t":176,"s":[840,831.48],"i":{"x":0,"y":0},"o":{"x":1,"y":1}},{"t":177,"s":[840,831.49],"i":{"x":0,"y":0},"o":{"x":1,"y":1}},{"t":178,"s":[840,831.5],"i":{"x":0,"y":0},"o":{"x":1,"y":1}}]},"r":{"a":0,"k":0},"s":{"a":0,"k":[133.33,133.33]},"sk":{"a":0,"k":0},"sa":{"a":0,"k":0}},"ao":0,"ip":0,"op":180,"st":0,"bm":0,"shapes":[{"ty":"gr","nm":"surface11","it":[{"ty":"gr","it":[{"ty":"sh","d":1,"ks":{"a":0,"k":{"c":true,"i":[[0,0],[0.57,-0.31],[0,0],[0,0],[0,0],[0.46,0],[0.41,0.23],[0,0],[0,0.68],[-0.57,0.31],[0,0],[0,0],[0,0],[-0.82,-0.45],[0,0],[0,-0.68]],"o":[[0,0.68],[0,0],[0,0],[0,0],[-0.41,0.23],[-0.46,0],[0,0],[-0.57,-0.31],[0,-0.68],[0,0],[0,0],[0,0],[0.82,-0.45],[0,0],[0.57,0.31],[0,0]],"v":[[20.63,6.43],[19.69,8.02],[17.51,9.2],[15.66,10.19],[11.82,12.26],[10.5,12.6],[9.18,12.26],[1.31,8.02],[0.38,6.43],[1.31,4.82],[3.77,3.5],[5.74,2.44],[9.18,0.59],[11.82,0.59],[19.69,4.82],[20.63,6.43]]}}},{"ty":"fl","c":{"a":0,"k":[1,1,1,1]},"r":1,"o":{"a":0,"k":100}},{"ty":"tr","nm":"Transform","a":{"a":0,"k":[0,0]},"o":{"a":0,"k":100},"p":{"a":0,"k":[0,0]},"r":{"a":0,"k":0},"s":{"a":0,"k":[100,100]},"sk":{"a":0,"k":0},"sa":{"a":0,"k":0}}]},{"ty":"tr","nm":"Transform","a":{"a":0,"k":[0,0]},"o":{"a":0,"k":100},"p":{"a":0,"k":[0,0]},"r":{"a":0,"k":0},"s":{"a":0,"k":[100,100]},"sk":{"a":0,"k":0},"sa":{"a":0,"k":0}}]}]},{"ddd":0,"ind":7,"ty":4,"ln":"layer_7","sr":1,"ks":{"a":{"a":0,"k":[15,15]},"o":{"a":0,"k":0},"p":{"a":0,"k":[840,840]},"r":{"a":0,"k":0},"s":{"a":0,"k":[133.33,133.33]},"sk":{"a":0,"k":0},"sa":{"a":0,"k":0}},"ao":0,"ip":0,"op":180,"st":0,"bm":0,"shapes":[{"ty":"gr","nm":"surface16","it":[{"ty":"tr","nm":"Transform","a":{"a":0,"k":[0,0]},"o":{"a":0,"k":100},"p":{"a":0,"k":[0,0]},"r":{"a":0,"k":0},"s":{"a":0,"k":[100,100]},"sk":{"a":0,"k":0},"sa":{"a":0,"k":0}}]}]}]},{"id":"oL6gqtAJV05jEO68zK0SZ","layers":[{"ddd":0,"ind":3,"ty":0,"nm":"","ln":"precomp_sU_jjh1PT6dhn1Ds8D7Xd3","sr":1,"ks":{"a":{"a":0,"k":[840,840]},"o":{"a":0,"k":100},"p":{"a":1,"k":[{"t":0,"s":[840,840],"i":{"x":0,"y":0},"o":{"x":1,"y":1}},{"t":1,"s":[840,839.86],"i":{"x":0,"y":0},"o":{"x":1,"y":1}},{"t":2,"s":[840,839.65],"i":{"x":0,"y":0},"o":{"x":1,"y":1}},{"t":3,"s":[840,839.36],"i":{"x":0,"y":0},"o":{"x":1,"y":1}},{"t":4,"s":[840,838.99],"i":{"x":0,"y":0},"o":{"x":1,"y":1}},{"t":5,"s":[840,838.54],"i":{"x":0,"y":0},"o":{"x":1,"y":1}},{"t":6,"s":[840,838.02],"i":{"x":0,"y":0},"o":{"x":1,"y":1}},{"t":7,"s":[840,837.45],"i":{"x":0,"y":0},"o":{"x":1,"y":1}},{"t":8,"s":[840,836.86],"i":{"x":0,"y":0},"o":{"x":1,"y":1}},{"t":9,"s":[840,836.27],"i":{"x":0,"y":0},"o":{"x":1,"y":1}},{"t":10,"s":[840,835.69],"i":{"x":0,"y":0},"o":{"x":1,"y":1}},{"t":11,"s":[840,835.15],"i":{"x":0,"y":0},"o":{"x":1,"y":1}},{"t":12,"s":[840,834.63],"i":{"x":0,"y":0},"o":{"x":1,"y":1}},{"t":13,"s":[840,834.16],"i":{"x":0,"y":0},"o":{"x":1,"y":1}},{"t":14,"s":[840,833.72],"i":{"x":0,"y":0},"o":{"x":1,"y":1}},{"t":15,"s":[840,833.32],"i":{"x":0,"y":0},"o":{"x":1,"y":1}},{"t":16,"s":[840,832.95],"i":{"x":0,"y":0},"o":{"x":1,"y":1}},{"t":17,"s":[840,832.62],"i":{"x":0,"y":0},"o":{"x":1,"y":1}},{"t":18,"s":[840,832.31],"i":{"x":0,"y":0},"o":{"x":1,"y":1}},{"t":19,"s":[840,832.03],"i":{"x":0,"y":0},"o":{"x":1,"y":1}},{"t":20,"s":[840,831.78],"i":{"x":0,"y":0},"o":{"x":1,"y":1}},{"t":21,"s":[840,831.55],"i":{"x":0,"y":0},"o":{"x":1,"y":1}},{"t":22,"s":[840,831.35],"i":{"x":0,"y":0},"o":{"x":1,"y":1}},{"t":23,"s":[840,831.16],"i":{"x":0,"y":0},"o":{"x":1,"y":1}},{"t":24,"s":[840,830.99],"i":{"x":0,"y":0},"o":{"x":1,"y":1}},{"t":25,"s":[840,830.84],"i":{"x":0,"y":0},"o":{"x":1,"y":1}},{"t":26,"s":[840,830.7],"i":{"x":0,"y":0},"o":{"x":1,"y":1}},{"t":27,"s":[840,830.58],"i":{"x":0,"y":0},"o":{"x":1,"y":1}},{"t":28,"s":[840,830.47],"i":{"x":0,"y":0},"o":{"x":1,"y":1}},{"t":29,"s":[840,830.38],"i":{"x":0,"y":0},"o":{"x":1,"y":1}},{"t":30,"s":[840,830.3],"i":{"x":0,"y":0},"o":{"x":1,"y":1}},{"t":31,"s":[840,830.23],"i":{"x":0,"y":0},"o":{"x":1,"y":1}},{"t":32,"s":[840,830.17],"i":{"x":0,"y":0},"o":{"x":1,"y":1}},{"t":33,"s":[840,830.12],"i":{"x":0,"y":0},"o":{"x":1,"y":1}},{"t":34,"s":[840,830.08],"i":{"x":0,"y":0},"o":{"x":1,"y":1}},{"t":35,"s":[840,830.05],"i":{"x":0,"y":0},"o":{"x":1,"y":1}},{"t":36,"s":[840,830.02],"i":{"x":0,"y":0},"o":{"x":1,"y":1}},{"t":37,"s":[840,830.01],"i":{"x":0,"y":0},"o":{"x":1,"y":1}},{"t":38,"s":[840,830],"i":{"x":0,"y":0},"o":{"x":1,"y":1}},{"t":39,"s":[840,830.07],"i":{"x":0,"y":0},"o":{"x":1,"y":1}},{"t":40,"s":[840,830.25],"i":{"x":0,"y":0},"o":{"x":1,"y":1}},{"t":41,"s":[840,830.5],"i":{"x":0,"y":0},"o":{"x":1,"y":1}},{"t":42,"s":[840,830.84],"i":{"x":0,"y":0},"o":{"x":1,"y":1}},{"t":43,"s":[840,831.25],"i":{"x":0,"y":0},"o":{"x":1,"y":1}},{"t":44,"s":[840,831.74],"i":{"x":0,"y":0},"o":{"x":1,"y":1}},{"t":45,"s":[840,832.29],"i":{"x":0,"y":0},"o":{"x":1,"y":1}},{"t":46,"s":[840,832.87],"i":{"x":0,"y":0},"o":{"x":1,"y":1}},{"t":47,"s":[840,833.47],"i":{"x":0,"y":0},"o":{"x":1,"y":1}},{"t":48,"s":[840,834.05],"i":{"x":0,"y":0},"o":{"x":1,"y":1}},{"t":49,"s":[840,834.62],"i":{"x":0,"y":0},"o":{"x":1,"y":1}},{"t":50,"s":[840,835.15],"i":{"x":0,"y":0},"o":{"x":1,"y":1}},{"t":51,"s":[840,835.64],"i":{"x":0,"y":0},"o":{"x":1,"y":1}},{"t":52,"s":[840,836.09],"i":{"x":0,"y":0},"o":{"x":1,"y":1}},{"t":53,"s":[840,836.51],"i":{"x":0,"y":0},"o":{"x":1,"y":1}},{"t":54,"s":[840,836.89],"i":{"x":0,"y":0},"o":{"x":1,"y":1}},{"t":55,"s":[840,837.24],"i":{"x":0,"y":0},"o":{"x":1,"y":1}},{"t":56,"s":[840,837.56],"i":{"x":0,"y":0},"o":{"x":1,"y":1}},{"t":57,"s":[840,837.85],"i":{"x":0,"y":0},"o":{"x":1,"y":1}},{"t":58,"s":[840,838.11],"i":{"x":0,"y":0},"o":{"x":1,"y":1}},{"t":59,"s":[840,838.35],"i":{"x":0,"y":0},"o":{"x":1,"y":1}},{"t":60,"s":[840,838.56],"i":{"x":0,"y":0},"o":{"x":1,"y":1}},{"t":61,"s":[840,838.76],"i":{"x":0,"y":0},"o":{"x":1,"y":1}},{"t":62,"s":[840,838.94],"i":{"x":0,"y":0},"o":{"x":1,"y":1}},{"t":63,"s":[840,839.1],"i":{"x":0,"y":0},"o":{"x":1,"y":1}},{"t":64,"s":[840,839.24],"i":{"x":0,"y":0},"o":{"x":1,"y":1}},{"t":65,"s":[840,839.37],"i":{"x":0,"y":0},"o":{"x":1,"y":1}},{"t":66,"s":[840,839.48],"i":{"x":0,"y":0},"o":{"x":1,"y":1}},{"t":67,"s":[840,839.58],"i":{"x":0,"y":0},"o":{"x":1,"y":1}},{"t":68,"s":[840,839.67],"i":{"x":0,"y":0},"o":{"x":1,"y":1}},{"t":69,"s":[840,839.74],"i":{"x":0,"y":0},"o":{"x":1,"y":1}},{"t":70,"s":[840,839.81],"i":{"x":0,"y":0},"o":{"x":1,"y":1}},{"t":71,"s":[840,839.86],"i":{"x":0,"y":0},"o":{"x":1,"y":1}},{"t":72,"s":[840,839.91],"i":{"x":0,"y":0},"o":{"x":1,"y":1}},{"t":73,"s":[840,839.94],"i":{"x":0,"y":0},"o":{"x":1,"y":1}},{"t":74,"s":[840,839.97],"i":{"x":0,"y":0},"o":{"x":1,"y":1}},{"t":75,"s":[840,839.99],"i":{"x":0,"y":0},"o":{"x":1,"y":1}},{"t":76,"s":[840,840],"i":{"x":0,"y":0},"o":{"x":1,"y":1}}]},"r":{"a":0,"k":0},"s":{"a":0,"k":[100,100]},"sk":{"a":0,"k":0},"sa":{"a":0,"k":0}},"ao":0,"w":1680,"h":1680,"ip":0,"op":180,"st":0,"bm":0,"refId":"1cQeGCHnzN_vrrBmPHODg"}]},{"id":"xhDr_-dRgWuK6rekZdRAN","layers":[{"ddd":0,"ind":2,"ty":0,"nm":"","ln":"precomp_bd9NynIzuSmkmoocTfXkN2","sr":1,"ks":{"a":{"a":0,"k":[840,840]},"o":{"a":0,"k":100},"p":{"a":0,"k":[840,840]},"r":{"a":0,"k":0},"s":{"a":0,"k":[100,100]},"sk":{"a":0,"k":0},"sa":{"a":0,"k":0}},"ao":0,"w":1680,"h":1680,"ip":0,"op":180,"st":0,"bm":0,"refId":"oL6gqtAJV05jEO68zK0SZ"}]}],"ddd":0,"fr":60,"h":84,"ip":0,"layers":[{"ddd":0,"ind":1,"ty":0,"nm":"","ln":"precomp_xm9rbeZXqKfomPYdgS8mP1","sr":1,"ks":{"a":{"a":0,"k":[840,840]},"o":{"a":0,"k":100},"p":{"a":0,"k":[42.33,42]},"r":{"a":0,"k":0},"s":{"a":0,"k":[100,100]},"sk":{"a":0,"k":0},"sa":{"a":0,"k":0}},"ao":0,"w":1680,"h":1680,"ip":0,"op":180,"st":0,"bm":0,"refId":"xhDr_-dRgWuK6rekZdRAN"},{"ddd":0,"ind":8,"ty":4,"nm":"","ln":"xk8CAdfgnOQ8Dojy2Sxex","sr":1,"ks":{"a":{"a":0,"k":[0,0]},"o":{"a":0,"k":100},"p":{"a":0,"k":[42,42]},"r":{"a":0,"k":0},"s":{"a":0,"k":[100,100]},"sk":{"a":0,"k":0},"sa":{"a":0,"k":0}},"ao":0,"ip":0,"op":180,"st":0,"bm":0,"shapes":[{"ty":"gr","hd":false,"bm":0,"it":[{"ty":"rc","hd":false,"p":{"a":0,"k":[0,0]},"r":{"a":0,"k":16},"s":{"a":0,"k":[84,84]}},{"ty":"fl","hd":false,"bm":0,"c":{"a":0,"k":[0.314,0.455,0.957]},"r":1,"o":{"a":0,"k":100}},{"ty":"tr","nm":"Transform","a":{"a":0,"k":[0,0]},"o":{"a":0,"k":100},"p":{"a":0,"k":[0,0]},"r":{"a":0,"k":0},"s":{"a":0,"k":[100,100]},"sk":{"a":0,"k":0},"sa":{"a":0,"k":0}}],"np":0}]}],"meta":{"g":"https://jitter.video"},"nm":"delivery","op":180,"v":"5.7.4","w":84}